bhtsne.so
bhtsne_wrapper.so
wrapper.so
bhtsne/__init__.py
bhtsne/wrapper.so
bhtsne-0.1.9.dist-info/DESCRIPTION.rst
bhtsne-0.1.9.dist-info/METADATA
bhtsne-0.1.9.dist-info/RECORD
bhtsne-0.1.9.dist-info/WHEEL
bhtsne-0.1.9.dist-info/metadata.json
bhtsne-0.1.9.dist-info/top_level.txt
