Metadata-Version: 2.0
Name: bhtsne
Version: 0.1.9
Summary: Python module for Barnes-Hut implementation of t-SNE (Cython)
Home-page: https://github.com/dominiek/python-bhtsne
Author: UNKNOWN
Author-email: UNKNOWN
License: UNKNOWN
Platform: UNKNOWN
Requires-Dist: cython
Requires-Dist: numpy
